campy/__init__.py
campy/__version__.py
campy/datastructures/__init__.py
campy/datastructures/basicgraph.py
campy/datastructures/basicqueue.py
campy/datastructures/basicstack.py
campy/datastructures/graph.py
campy/datastructures/grid.py
campy/datastructures/lexicon.py
campy/datastructures/linkedlist.py
campy/datastructures/pqueue.py
campy/datastructures/queue.py
campy/datastructures/shuffle.py
campy/datastructures/sparsegrid.py
campy/graphics/__init__.py
campy/graphics/gbufferedimage.py
campy/graphics/gcolor.py
campy/graphics/gevents.py
campy/graphics/gfilechooser.py
campy/graphics/gfont.py
campy/graphics/gimage.py
campy/graphics/gmath.py
campy/graphics/gobjects.py
campy/graphics/goptionpane.py
campy/graphics/gtimer.py
campy/graphics/gtypes.py
campy/graphics/gwindow.py
campy/gui/__init__.py
campy/gui/ginteractors.py
campy/gui/events/__init__.py
campy/gui/events/key.py
campy/gui/events/mouse.py
campy/gui/events/timer.py
campy/gui/events/window.py
campy/io/__init__.py
campy/io/base64helper.py
campy/io/bitstream.py
campy/io/console.py
campy/io/filelib.py
campy/io/tokenscanner.py
campy/misc/__init__.py
campy/misc/easter.py
campy/misc/positivity.py
campy/private/__init__.py
campy/private/consolestreambuffer.py
campy/private/main.py
campy/private/platform.py
campy/private/backends/__init__.py
campy/private/backends/backend.py
campy/private/backends/backend_base.py
campy/private/backends/jbe/__init__.py
campy/private/backends/jbe/backend_jbe.py
campy/private/backends/jbe/jbepipe.py
campy/private/backends/jbe/platformat.py
campy/private/backends/jbe/platformatter.py
campy/private/backends/tk/__init__.py
campy/private/backends/tk/backend_tk.py
campy/private/backends/tk/menu.py
campy/stanford/__init__.py
campy/system/__init__.py
campy/system/error.py
campy/util/__init__.py
campy/util/decorators.py
campy/util/direction.py
campy/util/note.py
campy/util/observable.py
campy/util/point.py
campy/util/randomgenerator.py
campy/util/recursion.py
campy/util/simpio.py
campy-0.0.1.dev19.dist-info/LICENSE
campy-0.0.1.dev19.dist-info/METADATA
campy-0.0.1.dev19.dist-info/WHEEL
campy-0.0.1.dev19.dist-info/top_level.txt
campy-0.0.1.dev19.dist-info/RECORD
