Metadata-Version: 2.1
Name: campy
Version: 0.0.1.dev19
Summary: Stanford's introductory libraries in Python, including the ACM graphical libraries.
Home-page: https://campy.sredmond.io
Author: Sam Redmond
Author-email: sredmond@stanford.edu
License: MIT
Project-URL: Source, https://github.com/sredmond/campy/
Project-URL: Bug Reports, https://github.com/sredmond/campy/issues
Project-URL: Say Thanks!, http://saythanks.io/to/sredmond
Keywords: Stanford teaching education intro introductory ACM graphics CS106A CS106B CS106X CS106AP Karel GObject GOval GRect GWindow
Platform: UNKNOWN
Classifier: Development Status :: 3 - Alpha
Classifier: Intended Audience :: Developers
Classifier: Intended Audience :: Education
Classifier: License :: OSI Approved :: MIT License
Classifier: Topic :: Education
Classifier: Topic :: Software Development :: User Interfaces
Classifier: Programming Language :: Python :: 3
Classifier: Programming Language :: Python :: 3.4
Classifier: Programming Language :: Python :: 3.5
Classifier: Programming Language :: Python :: 3.6
Classifier: Programming Language :: Python :: 3.7
Requires-Python: >=3.4, <4
Provides-Extra: dev
Requires-Dist: check-manifest ; extra == 'dev'
Requires-Dist: pycodestyle ; extra == 'dev'
Provides-Extra: test
Requires-Dist: tox ; extra == 'test'
Requires-Dist: pytest ; extra == 'test'
Requires-Dist: pytest-cov ; extra == 'test'
Requires-Dist: coverage ; extra == 'test'
Provides-Extra: with-pillow
Requires-Dist: Pillow ; extra == 'with-pillow'
